metagene/__init__.py
metagene/annotation.py
metagene/cli.py
metagene/config.py
metagene/download.py
metagene/gtf.py
metagene/io.py
metagene/overlap.py
metagene/plotting.py
metagene/utils.py
metagene-0.0.15.dist-info/METADATA
metagene-0.0.15.dist-info/WHEEL
metagene-0.0.15.dist-info/entry_points.txt
metagene-0.0.15.dist-info/RECORD
