Metadata-Version: 2.4
Name: metagene
Version: 0.0.15
Summary: Metagene Profiling Analysis and Visualization
Project-URL: Repository, https://github.com/y9c/metagene
Author-email: Ye Chang <yech1990@gmail.com>
License-Expression: MIT
Keywords: DNA,RNA,biology,metagene
Requires-Python: >=3.12
Requires-Dist: matplotlib<4,>=3.0.0
Requires-Dist: pandas>=2.2.3
Requires-Dist: polars>=1.30.0
Requires-Dist: pyarrow
Requires-Dist: pyranges1>=1.0.13
Requires-Dist: rich-click<2,>=1.6.1
